{
  "error": null,
  "last_update": 1722348100,
  "call_center": "18006936",
  "rank_info": [
    {
      "id": 1,
      "name": "Mới",
      "min": 0,
      "max": 99,
      "gradients": [
        "#FF9522",
        "#DA5409"
      ],
      "icon": "https://minio.thecoffeehouse.com/image/tchmobileapp/membercard/Member.png",
      "benefits": []
    },
    {
      "id": 2,
      "name": "Đồng",
      "min": 100,
      "max": 199,
      "gradients": [
        "#876F5D",
        "#30292F"
      ],
      "icon": "https://minio.thecoffeehouse.com/image/tchmobileapp/membercard/Bronze.png",
      "benefits": [
        {
          "icon": "https://minio.thecoffeehouse.com/image/tchmobileapp/877_v5Membership2birthdayCake.png",
          "name": "Tặng 01 phần bánh sinh nhật"
        },
        {
          "icon": "https://minio.thecoffeehouse.com/image/tchmobileapp/879_v5Membership2snack.png",
          "name": "Miễn phí 01 phần Snack cho đơn hàng trên 100,000đ"
        },
        {
          "icon": "https://minio.thecoffeehouse.com/image/tchmobileapp/881_v5Membership2store.png",
          "name": "Đặc quyền Đổi Ưu đãi bằng điểm BEAN tích lũy"
        }
      ]
    },
    {
      "id": 3,
      "name": "Bạc",
      "min": 200,
      "max": 499,
      "gradients": [
        "#CBD7E4",
        "#65798E"
      ],
      "icon": "https://minio.thecoffeehouse.com/image/tchmobileapp/membercard/Silver.png",
      "benefits": [
        {
          "icon": "https://minio.thecoffeehouse.com/image/tchmobileapp/877_v5Membership2birthdayCake.png",
          "name": "Tặng 01 phần bánh sinh nhật"
        },
        {
          "icon": "https://minio.thecoffeehouse.com/image/tchmobileapp/882_v5Membership2voucher.png",
          "name": "Ưu đãi Mua 2 tặng 1"
        },
        {
          "icon": "https://minio.thecoffeehouse.com/image/tchmobileapp/881_v5Membership2store.png",
          "name": "Đặc quyền Đổi Ưu đãi bằng điểm BEAN tích lũy"
        }
      ]
    },
    {
      "id": 4,
      "name": "Vàng",
      "min": 500,
      "max": 2999,
      "gradients": [
        "#EEDB8B",
        "#F1B56B",
        "#E7AC4F",
        "#EDC87B",
        "#BE7F3C"
      ],
      "icon": "https://minio.thecoffeehouse.com/image/tchmobileapp/membercard/Gold.png",
      "benefits": [
        {
          "icon": "https://minio.thecoffeehouse.com/image/tchmobileapp/877_v5Membership2birthdayCake.png",
          "name": "Tặng 01 phần bánh sinh nhật"
        },
        {
          "icon": "https://minio.thecoffeehouse.com/image/tchmobileapp/878_v5Membership2coffeeCup.png",
          "name": "Miễn phí 1 phần nước Cà phê / Trà"
        },
        {
          "icon": "https://minio.thecoffeehouse.com/image/tchmobileapp/881_v5Membership2store.png",
          "name": "Đặc quyền Đổi Ưu đãi bằng điểm BEAN tích lũy"
        }
      ]
    },
    {
      "id": 5,
      "name": "Kim Cương",
      "min": 3000,
      "max": null,
      "gradients": [
        "#767676",
        "#414141",
        "#181818",
        "#000000"
      ],
      "icon": "https://minio.thecoffeehouse.com/image/tchmobileapp/membercard/Diamon.png",
      "benefits": [
        {
          "icon": "https://minio.thecoffeehouse.com/image/tchmobileapp/876_v5Membership2bean.png",
          "name": "Được nhân 1.5 BEAN tích lũy"
        },
        {
          "icon": "https://minio.thecoffeehouse.com/image/tchmobileapp/877_v5Membership2birthdayCake.png",
          "name": "Tặng 01 phần bánh sinh nhật"
        },
        {
          "icon": "https://minio.thecoffeehouse.com/image/tchmobileapp/878_v5Membership2coffeeCup.png",
          "name": "Miễn phí 01 phần nước bất kì"
        },
        {
          "icon": "https://minio.thecoffeehouse.com/image/tchmobileapp/882_v5Membership2voucher.png",
          "name": "Nhận riêng Ưu đãi từ The Coffee House và đối tác khác"
        },
        {
          "icon": "https://minio.thecoffeehouse.com/image/tchmobileapp/880_v5Membership2star.png",
          "name": "Cơ hội trải nghiệm & hưởng đặc quyền đầu tiên"
        },
        {
          "icon": "https://minio.thecoffeehouse.com/image/tchmobileapp/881_v5Membership2store.png",
          "name": "Đặc quyền Đổi Ưu đãi bằng điểm BEAN tích lũy"
        }
      ]
    }
  ],
  "payments": [
    {
      "text": "Tiền mặt",
      "method": "COD",
      "key": "COD",
      "image": "https://minio.thecoffeehouse.com/image/tchmobileapp/1000_photo_2021-04-06_11-17-08.jpg",
      "desc": ""
    },
    {
      "text": "MoMo",
      "method": "Momo",
      "key": "MoMo",
      "image": "https://minio.thecoffeehouse.com/image/tchmobileapp/386_ic_momo@3x.png",
      "desc": ""
    },
    {
      "text": "ZaloPay",
      "method": "ZaloPay",
      "key": "ZaloPay",
      "image": "https://minio.thecoffeehouse.com/image/tchmobileapp/388_ic_zalo@3x.png",
      "desc": ""
    },
    {
      "text": "ShopeePay",
      "method": "AirPay",
      "key": "AirPay",
      "image": "https://minio.thecoffeehouse.com/image/tchmobileapp/1120_1119_ShopeePay-Horizontal2_O.png",
      "desc": ""
    },
    {
      "text": "Thẻ ngân hàng",
      "method": "123pay",
      "key": "123pay",
      "image": "https://minio.thecoffeehouse.com/image/tchmobileapp/385_ic_atm@3x.png",
      "desc": "Chấp nhận các thẻ Visa, Master, Apple Pay"
    }
  ],
  "shipping_method": [
    "DELI",
    "PICKUP"
  ],
  "shipping_payments": {
    "DELI": [
      "VNPAY",
      "COD",
      "Momo",
      "ZaloPay",
      "AirPay",
      "123pay"
    ],
    "PICKUP": [
      "VNPAY",
      "Momo",
      "ZaloPay",
      "AirPay",
      "123pay"
    ],
    "TABLE": [
      "VNPAY",
      "Momo",
      "ZaloPay",
      "AirPay",
      "123pay"
    ]
  },
  "cancel_reasons": [
    {
      "id": "PAYMENT_FAIL",
      "text": "Thanh toán chưa thành công"
    },
    {
      "id": "INVALID_INFO",
      "text": "Thay đổi địa chỉ nhận hàng"
    },
    {
      "id": "CHANGE_FOOD",
      "text": "Thay đổi món"
    },
    {
      "id": "NOT_WANT",
      "text": "Không còn nhu cầu"
    },
    {
      "id": "MISS_COUPON",
      "text": "Quên nhập Mã ưu đãi"
    }
  ],
  "rating_categories": {
    "stores": [
      {
        "id": 0,
        "text": "Không, tất cả đều tốt"
      },
      {
        "id": 1,
        "text": "Không gian"
      },
      {
        "id": 2,
        "text": "Âm thanh"
      },
      {
        "id": 3,
        "text": "Nhân viên"
      },
      {
        "id": 4,
        "text": "Đồ uống"
      },
      {
        "id": 5,
        "text": "Thức ăn"
      },
      {
        "id": 6,
        "text": "Thời gian phục vụ"
      },
      {
        "id": 7,
        "text": "Wifi"
      }
    ],
    "deliveries": [
      {
        "id": 0,
        "text": "Không, tất cả đều tốt"
      },
      {
        "id": 1,
        "text": "Thời gian giao hàng"
      },
      {
        "id": 2,
        "text": "Ứng dụng"
      },
      {
        "id": 3,
        "text": "Nhân viên"
      },
      {
        "id": 4,
        "text": "Chất lượng sản phẩm"
      }
    ]
  },
  "timezone": "Asia/Ho_Chi_Minh",
  "default_string": {
    "schedule_day": "15-30 phút",
    "schedule_time": "Càng sớm càng tốt"
  },
  "web_links": {
    "story": "https://thecoffeehouse.com/pages/chuyen-ca-phe-va-tra",
    "help": "https://thecoffeehouse.com/pages/dieu-khoan-su-dung",
    "press_release": "https://order.thecoffeehouse.com/blogs/thong-cao-bao-chi",
    "reward": "https://order.thecoffeehouse.com/user-info/userBenefit",
    "term": "https://thecoffeehouse.com/pages/dieu-khoan-su-dung",
    "termVNPay": "https://order.thecoffeehouse.com/vnpay-term-app",
    "termPrepaid": null,
    "invoicingInstruct": "https://thecoffeehouse.com/pages/huong-dan-xuat-hoa-don-gtgt"
  },
  "ping_device_connected": "http://172.16.0.99:2777/user_ip_mapping",
  "update_optional": false,
  "update_required": false,
  "shipping_freq": 5,
  "auth_haravan": "https://accounts.haravan.com/connect/authorize?response_type=code&prompt=login&scope=offline_access%20openid%20profile%20email%20org%20userinfo%20hr_api.read_emp_basic&client_id=6ce913e5327930cb11c10b1300519edb&redirect_uri=tch%3A//guestapp",
  "staging_host": "",
  "gms_api_keys": [
    "AIzaSyB7pv9az-ak9TIdKyhGX9AFXHQRLBoPriU"
  ],
  "branding_image": "https://minio.thecoffeehouse.com/image/tchmobileapp/1132_logo%20TCH%20summer-1.png",
  "media_background": null,
  "event_cards": [],
  "feedback_orders": 3,
  "list_table": [
    "101",
    "102",
    "103",
    "104",
    "105",
    "106",
    "107",
    "108",
    "109",
    "110",
    "111",
    "112",
    "113",
    "114",
    "115",
    "116",
    "117",
    "118",
    "119",
    "120",
    "121",
    "122",
    "123",
    "124",
    "125",
    "126",
    "127",
    "128",
    "129",
    "130",
    "131",
    "132",
    "133",
    "134",
    "135",
    "136",
    "137",
    "138",
    "139",
    "140",
    "141",
    "142",
    "143",
    "144",
    "145",
    "146",
    "147",
    "148",
    "149",
    "150",
    "151",
    "152",
    "153",
    "154",
    "155",
    "156",
    "157",
    "158",
    "159",
    "160",
    "161",
    "162",
    "163",
    "164",
    "165",
    "166",
    "167",
    "168",
    "169",
    "170",
    "171",
    "172",
    "173",
    "174",
    "175",
    "176",
    "177",
    "178",
    "179",
    "180",
    "181",
    "182",
    "183",
    "184",
    "185",
    "186",
    "187",
    "188",
    "189",
    "190",
    "191",
    "192",
    "193",
    "194",
    "195",
    "196",
    "197",
    "198",
    "199",
    "201",
    "202",
    "203",
    "204",
    "205",
    "206",
    "207",
    "208",
    "209",
    "210",
    "211",
    "212",
    "213",
    "214",
    "215",
    "216",
    "217",
    "218",
    "219",
    "220",
    "221",
    "222",
    "223",
    "224",
    "225",
    "226",
    "227",
    "228",
    "229",
    "230",
    "231",
    "232",
    "233",
    "234",
    "235",
    "236",
    "237",
    "238",
    "239",
    "240",
    "241",
    "242",
    "243",
    "244",
    "245",
    "246",
    "247",
    "248",
    "249",
    "250",
    "251",
    "252",
    "253",
    "254",
    "255",
    "256",
    "257",
    "258",
    "259",
    "260",
    "261",
    "262",
    "263",
    "264",
    "265",
    "266",
    "267",
    "268",
    "269",
    "270",
    "271",
    "272",
    "273",
    "274",
    "275",
    "276",
    "277",
    "278",
    "279",
    "280",
    "281",
    "282",
    "283",
    "284",
    "285",
    "286",
    "287",
    "288",
    "289",
    "290",
    "291",
    "292",
    "293",
    "294",
    "295",
    "296",
    "297",
    "298",
    "299",
    "301",
    "302",
    "303",
    "304",
    "305",
    "306",
    "307",
    "308",
    "309",
    "310",
    "311",
    "312",
    "313",
    "314",
    "315",
    "316",
    "317",
    "318",
    "319",
    "320",
    "321",
    "322",
    "323",
    "324",
    "325",
    "326",
    "327",
    "328",
    "329",
    "330",
    "331",
    "332",
    "333",
    "334",
    "335",
    "336",
    "337",
    "338",
    "339",
    "340",
    "341",
    "342",
    "343",
    "344",
    "345",
    "346",
    "347",
    "348",
    "349",
    "350",
    "351",
    "352",
    "353",
    "354",
    "355",
    "356",
    "357",
    "358",
    "359",
    "360",
    "361",
    "362",
    "363",
    "364",
    "365",
    "366",
    "367",
    "368",
    "369",
    "370",
    "371",
    "372",
    "373",
    "374",
    "375",
    "376",
    "377",
    "378",
    "379",
    "380",
    "381",
    "382",
    "383",
    "384",
    "385",
    "386",
    "387",
    "388",
    "389",
    "390",
    "391",
    "392",
    "393",
    "394",
    "395",
    "396",
    "397",
    "398",
    "399",
    "401",
    "402",
    "403",
    "404",
    "405",
    "406",
    "407",
    "408",
    "409",
    "410",
    "411",
    "412",
    "413",
    "414",
    "415",
    "416",
    "417",
    "418",
    "419",
    "420",
    "421",
    "422",
    "423",
    "424",
    "425",
    "426",
    "427",
    "428",
    "429",
    "430",
    "431",
    "432",
    "433",
    "434",
    "435",
    "436",
    "437",
    "438",
    "439",
    "440",
    "441",
    "442",
    "443",
    "444",
    "445",
    "446",
    "447",
    "448",
    "449",
    "450",
    "451",
    "452",
    "453",
    "454",
    "455",
    "456",
    "457",
    "458",
    "459",
    "460",
    "461",
    "462",
    "463",
    "464",
    "465",
    "466",
    "467",
    "468",
    "469",
    "470",
    "471",
    "472",
    "473",
    "474",
    "475",
    "476",
    "477",
    "478",
    "479",
    "480",
    "481",
    "482",
    "483",
    "484",
    "485",
    "486",
    "487",
    "488",
    "489",
    "490",
    "491",
    "492",
    "493",
    "494",
    "495",
    "496",
    "497",
    "498",
    "499"
  ]
}